{
  "db_name": "PostgreSQL",
  "query": "INSERT INTO message_version (version_id, message_id, author_id, type, content, metadata, reply_id, mentions, embeds, created_at, override_name, created_seq, components)\n            VALUES ($1, $2, $3, $4, $5, $6, $7, $8, $9, $10, $11, $12, $13)",
  "describe": {
    "columns": [],
    "parameters": {
      "Left": [
        "Uuid",
        "Uuid",
        "Uuid",
        {
          "Custom": {
            "name": "message_type",
            "kind": {
              "Enum": [
                "DefaultMarkdown",
                "ThreadUpdate",
                "DefaultTagged",
                "ChannelRename",
                "MemberAdd",
                "MemberRemove",
                "MemberJoin",
                "MessagePinned",
                "ChannelIcon",
                "AutomodExecution",
                "ChannelMoved",
                "ChannelPingback",
                "Call",
                "ThreadCreated"
              ]
            }
          }
        },
        "Text",
        "Jsonb",
        "Uuid",
        "Jsonb",
        "Jsonb",
        "Timestamp",
        "Text",
        "Int8",
        "Jsonb"
      ]
    },
    "nullable": []
  },
  "hash": "9d7ec6d3466a42b9454dd47f59cb94bd3572e638c6d703834cdab77d84c908bf"
}
