{
  "db_name": "PostgreSQL",
  "query": "\n            select target_type, target_id, code, creator_id, created_at, expires_at, uses, max_uses, description\n            from invite\n            where code = $1\n            FOR UPDATE\n            ",
  "describe": {
    "columns": [
      {
        "ordinal": 0,
        "name": "target_type",
        "type_info": "Text"
      },
      {
        "ordinal": 1,
        "name": "target_id",
        "type_info": "Uuid"
      },
      {
        "ordinal": 2,
        "name": "code",
        "type_info": "Text"
      },
      {
        "ordinal": 3,
        "name": "creator_id",
        "type_info": "Uuid"
      },
      {
        "ordinal": 4,
        "name": "created_at",
        "type_info": "Timestamp"
      },
      {
        "ordinal": 5,
        "name": "expires_at",
        "type_info": "Timestamp"
      },
      {
        "ordinal": 6,
        "name": "uses",
        "type_info": "Int4"
      },
      {
        "ordinal": 7,
        "name": "max_uses",
        "type_info": "Int4"
      },
      {
        "ordinal": 8,
        "name": "description",
        "type_info": "Text"
      }
    ],
    "parameters": {
      "Left": [
        "Text"
      ]
    },
    "nullable": [
      false,
      true,
      false,
      false,
      false,
      true,
      false,
      true,
      true
    ]
  },
  "hash": "166c1ba855d704a5bedb711c7b583bb6e7de341efe1976ceda91a6a11b918161"
}
